[
 {
  "_doctype": "Case Record", 
  "_report": null, 
  "app": "dfactoring", 
  "blocked": 0, 
  "color": "#d9534f", 
  "custom": 0, 
  "docstatus": 0, 
  "doctype": "Desktop Icon", 
  "force_show": 0, 
  "hidden": 0, 
  "icon": "fa fa-microchip", 
  "label": "Case Record", 
  "link": "List/Case Record/List", 
  "modified": "2019-05-15 21:46:02.717295", 
  "module_name": "Case Record", 
  "name": "756b70339d", 
  "reverse": 0, 
  "standard": 1, 
  "type": "link"
 }, 
 {
  "_doctype": "Case File", 
  "_report": null, 
  "app": "dfactoring", 
  "blocked": 0, 
  "color": "#d9534f", 
  "custom": 0, 
  "docstatus": 0, 
  "doctype": "Desktop Icon", 
  "force_show": 0, 
  "hidden": 0, 
  "icon": "fa fa-microchip", 
  "label": "Case File", 
  "link": "List/Case File/List", 
  "modified": "2019-05-15 21:45:53.582565", 
  "module_name": "Case File", 
  "name": "5144852c4e", 
  "reverse": 0, 
  "standard": 1, 
  "type": "link"
 }, 
 {
  "_doctype": "Party Portfolio", 
  "_report": null, 
  "app": "dfactoring", 
  "blocked": 0, 
  "color": "#d9534f", 
  "custom": 0, 
  "docstatus": 0, 
  "doctype": "Desktop Icon", 
  "force_show": 0, 
  "hidden": 0, 
  "icon": "fa fa-microchip", 
  "label": "Party Portfolio", 
  "link": "List/Party Portfolio/List", 
  "modified": "2019-05-15 21:46:13.369719", 
  "module_name": "Party Portfolio", 
  "name": "e92608b3e6", 
  "reverse": 0, 
  "standard": 1, 
  "type": "link"
 }, 
 {
  "_doctype": "", 
  "_report": "Income by Portfolio", 
  "app": "dfactoring", 
  "blocked": 0, 
  "color": "#FFF168", 
  "custom": 0, 
  "docstatus": 0, 
  "doctype": "Desktop Icon", 
  "force_show": 0, 
  "hidden": 0, 
  "icon": null, 
  "label": "Income by Portfolio", 
  "link": "query-report/Income by Portfolio", 
  "modified": "2019-05-15 21:45:28.327718", 
  "module_name": "Income by Portfolio", 
  "name": "68bf837478", 
  "reverse": 0, 
  "standard": 1, 
  "type": "link"
 }
]